{
  "kind": "collectionType",
  "collectionName": "portfolios",
  "info": {
    "singularName": "portfolio",
    "pluralName": "portfolios",
    "displayName": "portfolio",
    "description": ""
  },
  "options": {
    "draftAndPublish": true
  },
  "pluginOptions": {},
  "attributes": {
    "title": {
      "type": "string",
      "required": true
    },
    "description": {
      "type": "blocks"
    },
    "featuredImage": {
      "type": "media",
      "multiple": false,
      "required": false,
      "allowedTypes": [
        "images",
        "files",
        "videos",
        "audios"
      ]
    },
    "fullVideo": {
      "type": "media",
      "multiple": false,
      "required": false,
      "allowedTypes": [
        "images",
        "files",
        "videos",
        "audios"
      ]
    },
    "snippetVideo": {
      "type": "media",
      "multiple": false,
      "required": false,
      "allowedTypes": [
        "images",
        "files",
        "videos",
        "audios"
      ]
    },
    "showcase": {
      "type": "boolean"
    },
    "productionRole": {
      "type": "string"
    },
    "clientName": {
      "type": "string"
    },
    "sortOrder": {
      "type": "integer"
    },
    "slug": {
      "type": "uid",
      "targetField": "title"
    },
    "category": {
      "type": "relation",
      "relation": "oneToOne",
      "target": "api::category.category"
    },
    "full_video_id_bunny": {
      "type": "string"
    },
    "snippet_video_id_bunny": {
      "type": "string"
    }
  }
}